pytest.py
_pytest/__init__.py
_pytest/_argcomplete.py
_pytest/_version.py
_pytest/cacheprovider.py
_pytest/capture.py
_pytest/compat.py
_pytest/debugging.py
_pytest/deprecated.py
_pytest/doctest.py
_pytest/faulthandler.py
_pytest/fixtures.py
_pytest/freeze_support.py
_pytest/helpconfig.py
_pytest/hookspec.py
_pytest/junitxml.py
_pytest/logging.py
_pytest/main.py
_pytest/monkeypatch.py
_pytest/nodes.py
_pytest/nose.py
_pytest/outcomes.py
_pytest/pastebin.py
_pytest/pathlib.py
_pytest/pytester.py
_pytest/python.py
_pytest/python_api.py
_pytest/recwarn.py
_pytest/reports.py
_pytest/resultlog.py
_pytest/runner.py
_pytest/setuponly.py
_pytest/setupplan.py
_pytest/skipping.py
_pytest/stepwise.py
_pytest/terminal.py
_pytest/tmpdir.py
_pytest/unittest.py
_pytest/warning_types.py
_pytest/warnings.py
_pytest/_code/__init__.py
_pytest/_code/code.py
_pytest/_code/source.py
_pytest/_io/__init__.py
_pytest/_io/saferepr.py
_pytest/assertion/__init__.py
_pytest/assertion/rewrite.py
_pytest/assertion/truncate.py
_pytest/assertion/util.py
_pytest/config/__init__.py
_pytest/config/argparsing.py
_pytest/config/exceptions.py
_pytest/config/findpaths.py
_pytest/mark/__init__.py
_pytest/mark/evaluate.py
_pytest/mark/legacy.py
_pytest/mark/structures.py
alauda_pytest-5.2.3.dist-info/LICENSE
alauda_pytest-5.2.3.dist-info/METADATA
alauda_pytest-5.2.3.dist-info/WHEEL
alauda_pytest-5.2.3.dist-info/entry_points.txt
alauda_pytest-5.2.3.dist-info/top_level.txt
alauda_pytest-5.2.3.dist-info/RECORD
