Metadata-Version: 2.1
Name: alauda-pytest
Version: 5.2.3
Summary: pytest: simple powerful testing with Python
Home-page: https://docs.pytest.org/en/latest/
Author: Holger Krekel, Bruno Oliveira, Ronny Pfannschmidt, Floris Bruynooghe, Brianna Laugher, Florian Bruhin and others
License: MIT license
Project-URL: Source, https://github.com/hanhouchao/pytest
Project-URL: Tracker, https://github.com/pytest-dev/pytest/issues
Keywords: test,unittest
Platform: unix
Platform: linux
Platform: osx
Platform: cygwin
Platform: win32
Classifier: Development Status :: 6 - Mature
Classifier: Intended Audience :: Developers
Classifier: License :: OSI Approved :: MIT License
Classifier: Operating System :: POSIX
Classifier: Operating System :: Microsoft :: Windows
Classifier: Operating System :: MacOS :: MacOS X
Classifier: Topic :: Software Development :: Testing
Classifier: Topic :: Software Development :: Libraries
Classifier: Topic :: Utilities
Classifier: Programming Language :: Python :: 3 :: Only
Classifier: Programming Language :: Python :: 3.5
Classifier: Programming Language :: Python :: 3.6
Classifier: Programming Language :: Python :: 3.7
Classifier: Programming Language :: Python :: 3.8
Requires-Python: >=3.5
Requires-Dist: py (>=1.5.0)
Requires-Dist: packaging
Requires-Dist: attrs (>=17.4.0)
Requires-Dist: more-itertools (>=4.0.0)
Requires-Dist: atomicwrites (>=1.0)
Requires-Dist: pluggy (<1.0,>=0.12)
Requires-Dist: wcwidth
Requires-Dist: pathlib2 (>=2.2.0) ; python_version < "3.6"
Requires-Dist: importlib-metadata (>=0.12) ; python_version < "3.8"
Requires-Dist: colorama ; sys_platform == "win32"
Provides-Extra: testing
Requires-Dist: argcomplete ; extra == 'testing'
Requires-Dist: hypothesis (>=3.56) ; extra == 'testing'
Requires-Dist: mock ; extra == 'testing'
Requires-Dist: nose ; extra == 'testing'
Requires-Dist: requests ; extra == 'testing'
Requires-Dist: xmlschema ; extra == 'testing'
